ashnazg/__init__.py
ashnazg/fairy.py
ashnazg-0.0.1.dist-info/LICENSE
ashnazg-0.0.1.dist-info/METADATA
ashnazg-0.0.1.dist-info/WHEEL
ashnazg-0.0.1.dist-info/top_level.txt
ashnazg-0.0.1.dist-info/RECORD
