Metadata-Version: 2.1
Name: ashnazg
Version: 0.0.1
Summary: A package for handling data in a FAIR way
Home-page: https://ashnazg.com/docs/lib/fairy/
Author: Xander
Author-email: xander@ashnazg.com
License: UNKNOWN
Platform: UNKNOWN
Classifier: Programming Language :: Python :: 3
Classifier: License :: OSI Approved :: MIT License
Classifier: Operating System :: OS Independent
Requires-Python: >=3.6
